yandex_ris/__init__.py
yandex_ris/cli.py
yandex_ris/crawler.py
yandex_ris/version.py
yandex_ris-0.1.2.dist-info/licenses/LICENSE
yandex_ris-0.1.2.dist-info/METADATA
yandex_ris-0.1.2.dist-info/WHEEL
yandex_ris-0.1.2.dist-info/entry_points.txt
yandex_ris-0.1.2.dist-info/top_level.txt
yandex_ris-0.1.2.dist-info/RECORD
