Metadata-Version: 2.4
Name: yandex-ris
Version: 0.1.2
Summary: A professional reverse image search and crawling tool that uses Yandex's image search engine to find and download similar images.
Home-page: https://github.com/BIGBALLON/yandex-ris
Author: BIGBALLON
Author-email: fm.bigballon@gmail.com
Project-URL: Bug Reports, https://github.com/BIGBALLON/yandex-ris/issues
Project-URL: Source, https://github.com/BIGBALLON/yandex_ris
Classifier: Development Status :: 4 - Beta
Classifier: Intended Audience :: Developers
Classifier: License :: OSI Approved :: MIT License
Classifier: Operating System :: OS Independent
Classifier: Programming Language :: Python :: 3
Classifier: Programming Language :: Python :: 3.8
Classifier: Programming Language :: Python :: 3.9
Classifier: Programming Language :: Python :: 3.10
Classifier: Programming Language :: Python :: 3.11
Classifier: Topic :: Software Development :: Libraries :: Python Modules
Classifier: Topic :: Internet :: WWW/HTTP :: Indexing/Search
Classifier: Topic :: Multimedia :: Graphics
Requires-Python: >=3.8
License-File: LICENSE
Requires-Dist: selenium>=4.18.1
Requires-Dist: webdriver-manager>=4.0.1
Requires-Dist: beautifulsoup4>=4.12.3
Requires-Dist: icrawler>=0.6.10
Requires-Dist: python-dateutil>=2.8.2
Requires-Dist: colorlog>=6.8.2
Requires-Dist: tqdm>=4.66.2
Requires-Dist: requests>=2.31.0
Requires-Dist: urllib3>=2.0.0
Requires-Dist: lxml>=5.1.0
Requires-Dist: pillow>=10.2.0
Dynamic: author
Dynamic: author-email
Dynamic: classifier
Dynamic: description
Dynamic: description-content-type
Dynamic: home-page
Dynamic: license-file
Dynamic: project-url
Dynamic: requires-dist
Dynamic: requires-python
Dynamic: summary
